dialog_api_key/__init__.py
dialog_api_key/plugin.py
dialog_api_key-0.6.0.dist-info/LICENSE
dialog_api_key-0.6.0.dist-info/METADATA
dialog_api_key-0.6.0.dist-info/WHEEL
dialog_api_key-0.6.0.dist-info/entry_points.txt
dialog_api_key-0.6.0.dist-info/RECORD
