Metadata-Version: 2.1
Name: dialog-api-key
Version: 0.6.0
Summary: Dialog's API Key authorization plugin.
Author: Walison Filipe
Author-email: walisonfilipe@hotmail.com
Requires-Python: >=3.10,<4.0
Classifier: Programming Language :: Python :: 3
Classifier: Programming Language :: Python :: 3.10
Classifier: Programming Language :: Python :: 3.11
Classifier: Programming Language :: Python :: 3.12
Requires-Dist: fastapi (>=0.109.2,<0.110.0)
Requires-Dist: python-decouple (>=3.8,<4.0)
